BeginnersbookJavaZifuchuanJiaochengChuyi/README.md
BeginnersbookJavaZifuchuanJiaochengChuyi/__init__.py
BeginnersbookJavaZifuchuanJiaochengChuyi/__main__.py
BeginnersbookJavaZifuchuanJiaochengChuyi/file.epub
BeginnersbookJavaZifuchuanJiaochengChuyi/index.html
BeginnersbookJavaZifuchuanJiaochengChuyi/css/__init__.py
BeginnersbookJavaZifuchuanJiaochengChuyi/css/annotations.css
BeginnersbookJavaZifuchuanJiaochengChuyi/css/main.css
BeginnersbookJavaZifuchuanJiaochengChuyi/css/normalize.css
BeginnersbookJavaZifuchuanJiaochengChuyi/css/popup.css
BeginnersbookJavaZifuchuanJiaochengChuyi/font/__init__.py
BeginnersbookJavaZifuchuanJiaochengChuyi/font/fontello.eot
BeginnersbookJavaZifuchuanJiaochengChuyi/font/fontello.svg
BeginnersbookJavaZifuchuanJiaochengChuyi/font/fontello.ttf
BeginnersbookJavaZifuchuanJiaochengChuyi/font/fontello.woff
BeginnersbookJavaZifuchuanJiaochengChuyi/img/__init__.py
BeginnersbookJavaZifuchuanJiaochengChuyi/img/annotator-glyph-sprite.png
BeginnersbookJavaZifuchuanJiaochengChuyi/img/annotator-icon-sprite.png
BeginnersbookJavaZifuchuanJiaochengChuyi/img/apple-touch-icon.png
BeginnersbookJavaZifuchuanJiaochengChuyi/img/cancelfullscreen.png
BeginnersbookJavaZifuchuanJiaochengChuyi/img/close.png
BeginnersbookJavaZifuchuanJiaochengChuyi/img/fullscreen.png
BeginnersbookJavaZifuchuanJiaochengChuyi/img/loader.gif
BeginnersbookJavaZifuchuanJiaochengChuyi/img/menu-icon.png
BeginnersbookJavaZifuchuanJiaochengChuyi/img/save.png
BeginnersbookJavaZifuchuanJiaochengChuyi/img/saved.png
BeginnersbookJavaZifuchuanJiaochengChuyi/img/settings-s.png
BeginnersbookJavaZifuchuanJiaochengChuyi/img/settings.png
BeginnersbookJavaZifuchuanJiaochengChuyi/img/star.png
BeginnersbookJavaZifuchuanJiaochengChuyi/js/__init__.py
BeginnersbookJavaZifuchuanJiaochengChuyi/js/epub.js
BeginnersbookJavaZifuchuanJiaochengChuyi/js/epub.min.js
BeginnersbookJavaZifuchuanJiaochengChuyi/js/epub.min.map
BeginnersbookJavaZifuchuanJiaochengChuyi/js/hooks.min.js
beginnersbook_java_zifuchuan_jiaocheng_chuyi-2024.3.5.0.dist-info/METADATA
beginnersbook_java_zifuchuan_jiaocheng_chuyi-2024.3.5.0.dist-info/WHEEL
beginnersbook_java_zifuchuan_jiaocheng_chuyi-2024.3.5.0.dist-info/entry_points.txt
beginnersbook_java_zifuchuan_jiaocheng_chuyi-2024.3.5.0.dist-info/top_level.txt
beginnersbook_java_zifuchuan_jiaocheng_chuyi-2024.3.5.0.dist-info/RECORD
